kaalin/__init__.py
kaalin/constants.py
kaalin/cli/__init__.py
kaalin/cli/converter.py
kaalin/converter/__init__.py
kaalin/converter/latin_cyrillic_converter.py
kaalin/number/__init__.py
kaalin/number/exceptions.py
kaalin/number/num2words.py
kaalin/string/__init__.py
kaalin/string/string_utils.py
kaalin-3.2.0.dist-info/licenses/LICENSE
test/__init__.py
test/test_kaalin_converter.py
test/test_kaalin_string.py
test/test_num2words.py
kaalin-3.2.0.dist-info/METADATA
kaalin-3.2.0.dist-info/WHEEL
kaalin-3.2.0.dist-info/entry_points.txt
kaalin-3.2.0.dist-info/top_level.txt
kaalin-3.2.0.dist-info/RECORD
