Metadata-Version: 2.4
Name: kaalin
Version: 3.2.0
Summary: Special opportunities for the Karakalpak language
Author: Turdıbek Jumabaev
Author-email: <turdibekjumabaev05@gmail.com>
Keywords: karakalpak,language,python
Classifier: Development Status :: 1 - Planning
Classifier: Intended Audience :: Developers
Classifier: Programming Language :: Python :: 3
Classifier: Operating System :: Unix
Classifier: Operating System :: MacOS :: MacOS X
Classifier: Operating System :: Microsoft :: Windows
License-File: LICENSE
Dynamic: author
Dynamic: author-email
Dynamic: classifier
Dynamic: description
Dynamic: description-content-type
Dynamic: keywords
Dynamic: license-file
Dynamic: summary
